xcnt_drivr_metadata_client-2022.9.2-py3.10-nspkg.pth
xcnt/drivr/metadata_client/__init__.py
xcnt/drivr/metadata_client/configuration.py
xcnt/drivr/metadata_client/enum.py
xcnt/drivr/metadata_client/registry.py
xcnt/drivr/metadata_client/runner.py
xcnt/drivr/metadata_client/command/__init__.py
xcnt/drivr/metadata_client/command/metadata_execution.py
xcnt/drivr/metadata_client/command/metadata_value_command.py
xcnt/drivr/metadata_client/command/validation/__init__.py
xcnt/drivr/metadata_client/command/validation/metadata_validation_checker.py
xcnt/drivr/metadata_client/command/validation/validator.py
xcnt/drivr/metadata_client/event/__init__.py
xcnt/drivr/metadata_client/event/metadata_type_events.py
xcnt/drivr/metadata_client/event/metadata_value.py
xcnt/drivr/metadata_client/lookup/__init__.py
xcnt/drivr/metadata_client/lookup/metadata_lookup.py
xcnt/drivr/metadata_client/lookup/metadata_type_lookup.py
xcnt/drivr/metadata_client/lookup/metadata_value_lookup.py
xcnt/drivr/metadata_client/marshmallow/__init__.py
xcnt/drivr/metadata_client/marshmallow/metadata_field.py
xcnt/drivr/metadata_client/marshmallow/metadata_field_schema_creator.py
xcnt/drivr/metadata_client/marshmallow/metadata_key_value_pair_schema_creator.py
xcnt/drivr/metadata_client/marshmallow/metadata_key_value_store.py
xcnt/drivr/metadata_client/marshmallow/metadata_key_value_store_field.py
xcnt/drivr/metadata_client/marshmallow/type_field.py
xcnt/drivr/metadata_client/model/__init__.py
xcnt/drivr/metadata_client/model/metadata_field.py
xcnt/drivr/metadata_client/model/metadata_type.py
xcnt/drivr/metadata_client/model/metadata_value.py
xcnt/drivr/metadata_client/search/__init__.py
xcnt/drivr/metadata_client/search/metadata_field.py
xcnt/drivr/metadata_client/search/metadata_item.py
xcnt/drivr/metadata_client/search/metadata_key_value_store_field.py
xcnt/drivr/metadata_client/search/metadata_type_key.py
xcnt/drivr/metadata_client/search/api_gateway_crd/__init__.py
xcnt_drivr_metadata_client-2022.9.2.dist-info/METADATA
xcnt_drivr_metadata_client-2022.9.2.dist-info/WHEEL
xcnt_drivr_metadata_client-2022.9.2.dist-info/entry_points.txt
xcnt_drivr_metadata_client-2022.9.2.dist-info/namespace_packages.txt
xcnt_drivr_metadata_client-2022.9.2.dist-info/top_level.txt
xcnt_drivr_metadata_client-2022.9.2.dist-info/RECORD
